wireguard/__init__.py
wireguard/constants.py
wireguard/exceptions.py
wireguard/functions.py
wireguard/handshake.py
wireguard/keypair.py
wireguard/packet_replay.py
wireguard/tai64n.py
wireguard/wireguard.py
wireguard/stack/__init__.py
wireguard/stack/icmp.py
wireguard/stack/internet_checksum.py
wireguard/stack/ip.py
wireguard/stack/ipv4.py
wireguard/stack/ipv6.py
wireguard/stack/protocols.py
wireguard/stack/registry.py
wireguard/stack/udp.py
wireguard/stack/tcp/__init__.py
wireguard/stack/tcp/tcp_exceptions.py
wireguard/stack/tcp/tcp_fsm.py
wireguard/stack/tcp/tcp_opt.py
wireguard/stack/tcp/tcp_pkt.py
wireguard_protocol-0.0.7.dist-info/licenses/LICENSE
wireguard_protocol-0.0.7.dist-info/METADATA
wireguard_protocol-0.0.7.dist-info/WHEEL
wireguard_protocol-0.0.7.dist-info/top_level.txt
wireguard_protocol-0.0.7.dist-info/RECORD
