Metadata-Version: 2.4
Name: wireguard-protocol
Version: 0.0.7
Summary: A pure Python implementation of WireGuard
Author-email: rafa_br34 <rafa_br34@exulan.com.au>
License-Expression: MIT
Project-URL: Homepage, https://github.com/rafa-br34/py-wg
Project-URL: Issues, https://github.com/rafa-br34/py-wg/issues
Classifier: Programming Language :: Python :: 3
Classifier: Operating System :: OS Independent
Requires-Python: >=3.10
License-File: LICENSE
Requires-Dist: pynacl>=1.5.0
Dynamic: license-file
